api_clients.py
config.py
constants.py
llm_config.py
main.py
solve.py
spinner.py
cs_assistant-0.1.4.dist-info/licenses/LICENSE
cs_assistant-0.1.4.dist-info/METADATA
cs_assistant-0.1.4.dist-info/WHEEL
cs_assistant-0.1.4.dist-info/entry_points.txt
cs_assistant-0.1.4.dist-info/top_level.txt
cs_assistant-0.1.4.dist-info/RECORD
