Metadata-Version: 2.4
Name: cs-assistant
Version: 0.1.4
Summary: CS Assistant
Author-email: German Velibekov <german.velibekov@gmail.com>
Requires-Python: >=3.8
License-File: LICENSE
Requires-Dist: openai>=1.76.0
Requires-Dist: google-generativeai>=0.8.5
Requires-Dist: python-dotenv>=1.1.0
Requires-Dist: colorama>=0.4.6
Requires-Dist: anthropic>=0.7.0
Dynamic: license-file
